[
  {
    "Type": "Texture2D",
    "Name": "T_UI_Outfits_Highlight",
    "Class": "UScriptClass'Texture2D'",
    "Flags": "RF_Public | RF_Standalone | RF_WasLoaded | RF_LoadCompleted",
    "Properties": {
      "ImportedSize": {
        "X": 296,
        "Y": 360
      },
      "LightingGuid": "55577F38-4FE7318C-1C03BD80-0E04E7D2",
      "CompressionSettings": "TextureCompressionSettings::TC_BC7",
      "LODGroup": "TextureGroup::TEXTUREGROUP_UI",
      "NeverStream": true
    },
    "SizeX": 296,
    "SizeY": 360,
    "PackedData": 1,
    "PixelFormat": "PF_BC7",
    "FirstMipToSerialize": 0,
    "Mips": [
      {
        "BulkData": {
          "BulkDataFlags": "BULKDATA_SingleUse | BULKDATA_ForceInlinePayload",
          "ElementCount": 106560,
          "SizeOnDisk": 106560,
          "OffsetInFile": "0x76"
        },
        "SizeX": 296,
        "SizeY": 360,
        "SizeZ": 1
      }
    ]
  }
]